sine.v
module sine_wave_generator (
    input  wire       clk,        // Fast system clock
    input  wire       rst,        // Active-high reset
    output reg  [7:0] sine_out    // 8-bit digital sine wave amplitude
);

    // 1. The Phase Accumulator (Counter)
    // We need 5 bits to address 32 different samples (2^5 = 32)
    reg [4:0] phase_acc;

    // 2. The Look-Up Table (ROM)
    // 32 memory locations, each 8 bits wide
    reg [7:0] sine_rom [0:31];

    // Initialize the ROM with pre-calculated sine values.
    // These values represent one full cycle of sin(x) scaled to 0-255 (8-bit unsigned).
    // Center point is 127. Peak is 255. Trough is 0.
    initial begin
        sine_rom[0]  = 8'd127; sine_rom[1]  = 8'd152; sine_rom[2]  = 8'd176; sine_rom[3]  = 8'd198;
        sine_rom[4]  = 8'd218; sine_rom[5]  = 8'd234; sine_rom[6]  = 8'd245; sine_rom[7]  = 8'd253;
        sine_rom[8]  = 8'd255; sine_rom[9]  = 8'd253; sine_rom[10] = 8'd245; sine_rom[11] = 8'd234;
        sine_rom[12] = 8'd218; sine_rom[13] = 8'd198; sine_rom[14] = 8'd176; sine_rom[15] = 8'd152;
        sine_rom[16] = 8'd127; sine_rom[17] = 8'd103; sine_rom[18] = 8'd79;  sine_rom[19] = 8'd57;
        sine_rom[20] = 8'd37;  sine_rom[21] = 8'd21;  sine_rom[22] = 8'd10;  sine_rom[23] = 8'd2;
        sine_rom[24] = 8'd0;   sine_rom[25] = 8'd2;   sine_rom[26] = 8'd10;  sine_rom[27] = 8'd21;
        sine_rom[28] = 8'd37;  sine_rom[29] = 8'd57;  sine_rom[30] = 8'd79;  sine_rom[31] = 8'd103;
    end

    // Sequential logic to drive the phase accumulator and fetch ROM data
    always @(posedge clk or posedge rst) begin
        if (rst) begin
            phase_acc <= 5'd0;
            sine_out  <= 8'd127; // Reset to the zero-crossing center value
        end else begin
            // Increment the counter. It will naturally roll over from 31 back to 0.
            phase_acc <= phase_acc + 1'b1;
            
            // Output the sine wave value at the current phase index
            sine_out  <= sine_rom[phase_acc];
        end
    end

endmodule

tb_sine.v
`timescale 1ns/1ps

module tb_sine_wave_generator;

    // Testbench signals
    reg clk;
    reg rst;
    wire [7:0] sine_out;

    // Instantiate DUT
    sine_wave_generator dut (
        .clk(clk),
        .rst(rst),
        .sine_out(sine_out)
    );

    // Clock generation (10 ns period)
    always #5 clk = ~clk;

    integer i;

    initial begin
        // Initialize
        clk = 0;
        rst = 1;

        // Apply reset
        #20;
        rst = 0;

        // Run for several cycles
        for (i = 0; i < 80; i = i + 1) begin
            @(posedge clk);
            $display("Time=%0t Phase=%0d Sine_out=%0d",
                      $time, dut.phase_acc, sine_out);
        end

        $finish;
    end

    // Optional waveform dump (for GTKWave / ModelSim)
    initial begin
        $dumpfile("sine_wave.vcd");
        $dumpvars(0, tb_sine_wave_generator);
    end

endmodule

sine_wave.vcd
$date
	Fri Mar 13 00:22:17 2026
$end
$version
	Icarus Verilog
$end
$timescale
	1ps
$end
$scope module tb_sine_wave_generator $end
$var wire 8 ! sine_out [7:0] $end
$var reg 1 " clk $end
$var reg 1 # rst $end
$var integer 32 $ i [31:0] $end
$scope module dut $end
$var wire 1 " clk $end
$var wire 1 # rst $end
$var reg 5 % phase_acc [4:0] $end
$var reg 8 & sine_out [7:0] $end
$upscope $end
$upscope $end
$enddefinitions $end
$comment Show the parameter values. $end
$dumpall
$end
#0
$dumpvars
b1111111 &
b0 %
bx $
1#
0"
b1111111 !
$end
#5000
1"
#10000
0"
#15000
1"
#20000
0"
b0 $
0#
#25000
b1 %
b1 $
1"
#30000
0"
#35000
b10011000 !
b10011000 &
b10 %
b10 $
1"
#40000
0"
#45000
b10110000 !
b10110000 &
b11 %
b11 $
1"
#50000
0"
#55000
b11000110 !
b11000110 &
b100 %
b100 $
1"
#60000
0"
#65000
b11011010 !
b11011010 &
b101 %
b101 $
1"
#70000
0"
#75000
b11101010 !
b11101010 &
b110 %
b110 $
1"
#80000
0"
#85000
b11110101 !
b11110101 &
b111 %
b111 $
1"
#90000
0"
#95000
b11111101 !
b11111101 &
b1000 %
b1000 $
1"
#100000
0"
#105000
b11111111 !
b11111111 &
b1001 %
b1001 $
1"
#110000
0"
#115000
b11111101 !
b11111101 &
b1010 %
b1010 $
1"
#120000
0"
#125000
b11110101 !
b11110101 &
b1011 %
b1011 $
1"
#130000
0"
#135000
b11101010 !
b11101010 &
b1100 %
b1100 $
1"
#140000
0"
#145000
b11011010 !
b11011010 &
b1101 %
b1101 $
1"
#150000
0"
#155000
b11000110 !
b11000110 &
b1110 %
b1110 $
1"
#160000
0"
#165000
b10110000 !
b10110000 &
b1111 %
b1111 $
1"
#170000
0"
#175000
b10011000 !
b10011000 &
b10000 %
b10000 $
1"
#180000
0"
#185000
b1111111 !
b1111111 &
b10001 %
b10001 $
1"
#190000
0"
#195000
b1100111 !
b1100111 &
b10010 %
b10010 $
1"
#200000
0"
#205000
b1001111 !
b1001111 &
b10011 %
b10011 $
1"
#210000
0"
#215000
b111001 !
b111001 &
b10100 %
b10100 $
1"
#220000
0"
#225000
b100101 !
b100101 &
b10101 %
b10101 $
1"
#230000
0"
#235000
b10101 !
b10101 &
b10110 %
b10110 $
1"
#240000
0"
#245000
b1010 !
b1010 &
b10111 %
b10111 $
1"
#250000
0"
#255000
b10 !
b10 &
b11000 %
b11000 $
1"
#260000
0"
#265000
b0 !
b0 &
b11001 %
b11001 $
1"
#270000
0"
#275000
b10 !
b10 &
b11010 %
b11010 $
1"
#280000
0"
#285000
b1010 !
b1010 &
b11011 %
b11011 $
1"
#290000
0"
#295000
b10101 !
b10101 &
b11100 %
b11100 $
1"
#300000
0"
#305000
b100101 !
b100101 &
b11101 %
b11101 $
1"
#310000
0"
#315000
b111001 !
b111001 &
b11110 %
b11110 $
1"
#320000
0"
#325000
b1001111 !
b1001111 &
b11111 %
b11111 $
1"
#330000
0"
#335000
b1100111 !
b1100111 &
b0 %
b100000 $
1"
#340000
0"
#345000
b1111111 !
b1111111 &
b1 %
b100001 $
1"
#350000
0"
#355000
b10011000 !
b10011000 &
b10 %
b100010 $
1"
#360000
0"
#365000
b10110000 !
b10110000 &
b11 %
b100011 $
1"
#370000
0"
#375000
b11000110 !
b11000110 &
b100 %
b100100 $
1"
#380000
0"
#385000
b11011010 !
b11011010 &
b101 %
b100101 $
1"
#390000
0"
#395000
b11101010 !
b11101010 &
b110 %
b100110 $
1"
#400000
0"
#405000
b11110101 !
b11110101 &
b111 %
b100111 $
1"
#410000
0"
#415000
b11111101 !
b11111101 &
b1000 %
b101000 $
1"
#420000
0"
#425000
b11111111 !
b11111111 &
b1001 %
b101001 $
1"
#430000
0"
#435000
b11111101 !
b11111101 &
b1010 %
b101010 $
1"
#440000
0"
#445000
b11110101 !
b11110101 &
b1011 %
b101011 $
1"
#450000
0"
#455000
b11101010 !
b11101010 &
b1100 %
b101100 $
1"
#460000
0"
#465000
b11011010 !
b11011010 &
b1101 %
b101101 $
1"
#470000
0"
#475000
b11000110 !
b11000110 &
b1110 %
b101110 $
1"
#480000
0"
#485000
b10110000 !
b10110000 &
b1111 %
b101111 $
1"
#490000
0"
#495000
b10011000 !
b10011000 &
b10000 %
b110000 $
1"
#500000
0"
#505000
b1111111 !
b1111111 &
b10001 %
b110001 $
1"
#510000
0"
#515000
b1100111 !
b1100111 &
b10010 %
b110010 $
1"
#520000
0"
#525000
b1001111 !
b1001111 &
b10011 %
b110011 $
1"
#530000
0"
#535000
b111001 !
b111001 &
b10100 %
b110100 $
1"
#540000
0"
#545000
b100101 !
b100101 &
b10101 %
b110101 $
1"
#550000
0"
#555000
b10101 !
b10101 &
b10110 %
b110110 $
1"
#560000
0"
#565000
b1010 !
b1010 &
b10111 %
b110111 $
1"
#570000
0"
#575000
b10 !
b10 &
b11000 %
b111000 $
1"
#580000
0"
#585000
b0 !
b0 &
b11001 %
b111001 $
1"
#590000
0"
#595000
b10 !
b10 &
b11010 %
b111010 $
1"
#600000
0"
#605000
b1010 !
b1010 &
b11011 %
b111011 $
1"
#610000
0"
#615000
b10101 !
b10101 &
b11100 %
b111100 $
1"
#620000
0"
#625000
b100101 !
b100101 &
b11101 %
b111101 $
1"
#630000
0"
#635000
b111001 !
b111001 &
b11110 %
b111110 $
1"
#640000
0"
#645000
b1001111 !
b1001111 &
b11111 %
b111111 $
1"
#650000
0"
#655000
b1100111 !
b1100111 &
b0 %
b1000000 $
1"
#660000
0"
#665000
b1111111 !
b1111111 &
b1 %
b1000001 $
1"
#670000
0"
#675000
b10011000 !
b10011000 &
b10 %
b1000010 $
1"
#680000
0"
#685000
b10110000 !
b10110000 &
b11 %
b1000011 $
1"
#690000
0"
#695000
b11000110 !
b11000110 &
b100 %
b1000100 $
1"
#700000
0"
#705000
b11011010 !
b11011010 &
b101 %
b1000101 $
1"
#710000
0"
#715000
b11101010 !
b11101010 &
b110 %
b1000110 $
1"
#720000
0"
#725000
b11110101 !
b11110101 &
b111 %
b1000111 $
1"
#730000
0"
#735000
b11111101 !
b11111101 &
b1000 %
b1001000 $
1"
#740000
0"
#745000
b11111111 !
b11111111 &
b1001 %
b1001001 $
1"
#750000
0"
#755000
b11111101 !
b11111101 &
b1010 %
b1001010 $
1"
#760000
0"
#765000
b11110101 !
b11110101 &
b1011 %
b1001011 $
1"
#770000
0"
#775000
b11101010 !
b11101010 &
b1100 %
b1001100 $
1"
#780000
0"
#785000
b11011010 !
b11011010 &
b1101 %
b1001101 $
1"
#790000
0"
#795000
b11000110 !
b11000110 &
b1110 %
b1001110 $
1"
#800000
0"
#805000
b10110000 !
b10110000 &
b1111 %
b1001111 $
1"
#810000
0"
#815000
b10011000 !
b10011000 &
b10000 %
b1010000 $
1"
